{
  "grantorSection": "#0",
  "granteeSection": "#1",
  "grantorPersonRadio": "[id=\"Grantor (Owner/Lessee)-person-0\"]",
  "grantorCompanyRadio": "[id=\"Grantor (Owner/Lessee)-company-0\"]",
  "granteePersonRadio": "[id=\"Grantee (Contractor)-person-1\"]",
  "granteeCompanyRadio": "[id=\"Grantee (Contractor)-company-1\"]",
  "grantorAddButton": "#0 button.add, #0 button.clone.add",
  "granteeAddButton": "#1 button.add, #1 button.clone.add",
  "saveButton": "#save-button, xpath=//*[normalize-space(.)=\"Save\"]",
  "documentOneLink": "a:has-text(\"Document 1\")",
  "deletePackage": "#DeletePkgBtn",
  "deleteConfirm": "#modal-submit"
}